{
  "TheAside": {
    "description": "Aside of the-component",
    "displayName": "TheAside",
    "methods": [
      {
        "name": "Container",
        "docblock": null,
        "modifiers": [
          "static"
        ],
        "params": [
          {
            "name": "{\n                    children,\n                    className,\n                  }",
            "type": null
          }
        ],
        "returns": null
      },
      {
        "name": "For",
        "docblock": null,
        "modifiers": [
          "static"
        ],
        "params": [
          {
            "name": "{\n              children,\n              className,\n            }",
            "type": null
          }
        ],
        "returns": null
      }
    ]
  },
  "TheAsideStyle": {
    "description": "Style for TheAside",
    "displayName": "TheAsideStyle",
    "methods": [],
    "props": {
      "options": {
        "type": {
          "name": "object"
        },
        "required": false,
        "description": "Style options",
        "defaultValue": {
          "value": "{}",
          "computed": false
        }
      }
    }
  }
}